{
  "parent": "minecraft:recipes/root",
  "criteria": {
    "has_ebony_helmet_forestry": {
      "conditions": {
        "items": [
          {
            "items": [
              "survivalplus:ebony_helmet_forestry"
            ]
          }
        ]
      },
      "trigger": "minecraft:inventory_changed"
    },
    "has_the_recipe": {
      "conditions": {
        "recipe": "survivalplus:ebony_helmet_forestry_repairing"
      },
      "trigger": "minecraft:recipe_unlocked"
    }
  },
  "requirements": [
    [
      "has_ebony_helmet_forestry",
      "has_the_recipe"
    ]
  ],
  "rewards": {
    "recipes": [
      "survivalplus:ebony_helmet_forestry_repairing"
    ]
  }
}