{
  "parent": "minecraft:recipes/root",
  "rewards": {
    "recipes": [
      "survivalplus:white_dye"
    ]
  },
  "criteria": {
    "has_onion": {
      "trigger": "minecraft:inventory_changed",
      "conditions": {
        "items": [
          {
            "tag": "forge:crops/onion"
          }
        ]
      }
    },
    "has_the_recipe": {
      "trigger": "minecraft:recipe_unlocked",
      "conditions": {
        "recipe": "survivalplus:white_dye"
      }
    }
  },
  "requirements": [
    [
      "has_onion",
      "has_the_recipe"
    ]
  ]
}